[
    {
        "code": 0,
        "routeID": "HSZ0008",
        "routeName": {
            "zh": "83",
            "en": "83"
        },
        "subroute": [
            {
                "subrouteID": "HSZ00080",
                "subrouteName": {
                    "zh": "83",
                    "en": "83"
                },
                "headsign": {
                    "zh": "成德路─清華大學",
                    "en": "ChengDe Rd-National Tsing Hua University"
                }
            },
            {
                "subrouteID": "HSZ00080",
                "subrouteName": {
                    "zh": "83",
                    "en": "83"
                },
                "headsign": {
                    "zh": "清華大學─成德路",
                    "en": "National Tsing Hua University-ChengDe Rd"
                }
            },
            {
                "subrouteID": "HSZ0008A",
                "subrouteName": {
                    "zh": "83支A",
                    "en": "83支A"
                },
                "headsign": {
                    "zh": "成德路─清華大學(區)",
                    "en": "ChengDe Rd-National Tsing Hua University"
                }
            },
            {
                "subrouteID": "HSZ0008A",
                "subrouteName": {
                    "zh": "83支A",
                    "en": "83支A"
                },
                "headsign": {
                    "zh": "清華大學─成德路(區)",
                    "en": "National Tsing Hua University-ChengDe Rd"
                }
            }
        ],
        "departure": {
            "zh": "成德路",
            "en": "Chengde Road"
        },
        "destination": {
            "zh": "北校門",
            "en": "North Campus"
        }
    },
    {
        "code": 0,
        "routeID": "HSZ0182",
        "routeName": {
            "zh": "182",
            "en": "182"
        },
        "subroute": [
            {
                "subrouteID": "HSZ01820",
                "subrouteName": {
                    "zh": "182",
                    "en": "182"
                },
                "headsign": {
                    "zh": "北大橋→高鐵新竹站",
                    "en": "Bei-Da Bridge→THSR Hsinchu Station"
                }
            },
            {
                "subrouteID": "HSZ01820",
                "subrouteName": {
                    "zh": "182",
                    "en": "182"
                },
                "headsign": {
                    "zh": "高鐵新竹站→北大橋",
                    "en": "THSR Hsinchu Station →Bei—Da Bridge"
                }
            }
        ],
        "departure": {
            "zh": "北大橋",
            "en": "Bei-Da Bridge"
        },
        "destination": {
            "zh": "高鐵新竹站",
            "en": "THSR Hsinchu Station"
        }
    },
    {
        "code": 0,
        "routeID": "HSZ0010",
        "routeName": {
            "zh": "藍線1區",
            "en": "藍線1區"
        },
        "subroute": [
            {
                "subrouteID": "HSZ00100",
                "subrouteName": {
                    "zh": "藍線1區",
                    "en": "藍線1區"
                },
                "headsign": {
                    "zh": "火車站→竹中[循環線]",
                    "en": "Train Station→Zhu Zhong→Train Station"
                }
            }
        ],
        "departure": {
            "zh": "火車站",
            "en": "Train Station"
        },
        "destination": {
            "zh": "火車站",
            "en": "Train Station"
        }
    },
    {
        "code": 1,
        "routeID": "THB1619",
        "routeName": {
            "zh": "1619",
            "en": "1619"
        },
        "subroute": [
            {
                "subrouteID": "THB16190",
                "subrouteName": {
                    "zh": "1619",
                    "en": "1619"
                },
                "headsign": {
                    "zh": "臺北→中港路→臺中",
                    "en": "Taipei→Zhonggang Rd.→Taichung"
                }
            },
            {
                "subrouteID": "THB16190",
                "subrouteName": {
                    "zh": "1619",
                    "en": "1619"
                },
                "headsign": {
                    "zh": "臺中→中港路→臺北",
                    "en": "Taichung→Zhonggang Rd.→Taipei"
                }
            },
            {
                "subrouteID": "THB1619A",
                "subrouteName": {
                    "zh": "1619A",
                    "en": "1619A"
                },
                "headsign": {
                    "zh": "臺北→中港路→臺中[臺北至朝馬班次、不停科技生活館]",
                    "en": "Taipei→Zhonggang Rd.→Taichung(Taipei→Zhaoma、no stops Science Park Life Hub)"
                }
            },
            {
                "subrouteID": "THB1619A",
                "subrouteName": {
                    "zh": "1619A",
                    "en": "1619A"
                },
                "headsign": {
                    "zh": "臺中→中港路→臺北[朝馬至臺北班次、不停科技生活館]",
                    "en": "Taichung→Zhonggang Rd.→Taipei(Zhaoma→Taipei、no stops Science Park Life Hub)"
                }
            },
            {
                "subrouteID": "THB1619B",
                "subrouteName": {
                    "zh": "1619B",
                    "en": "1619B"
                },
                "headsign": {
                    "zh": "臺北→中港路→臺中[不停科技生活館]",
                    "en": "Taipei→Zhonggang Rd.→Taichung(Not Via Science Park Life Hub)"
                }
            },
            {
                "subrouteID": "THB1619B",
                "subrouteName": {
                    "zh": "1619B",
                    "en": "1619B"
                },
                "headsign": {
                    "zh": "臺中→中港路→臺北[不停科技生活館]",
                    "en": "Taichung→Zhonggang Rd.→Taipei(Not Via Science Park Life Hub)"
                }
            }
        ],
        "departure": {
            "zh": "臺北轉運站",
            "en": "Taipei Bus Station"
        },
        "destination": {
            "zh": "國軍英雄館",
            "en": "Taichung HERO HOUSE"
        }
    },
    {
        "code": 1,
        "routeID": "THB1728",
        "routeName": {
            "zh": "1728",
            "en": "1728"
        },
        "subroute": [
            {
                "subrouteID": "THB17280",
                "subrouteName": {
                    "zh": "1728",
                    "en": "1728"
                },
                "headsign": {
                    "zh": "臺北市→國道3號、1號→新竹市",
                    "en": "Taipei City→National Freeway No. 3 and No.1→Hsinchu City"
                }
            },
            {
                "subrouteID": "THB17280",
                "subrouteName": {
                    "zh": "1728",
                    "en": "1728"
                },
                "headsign": {
                    "zh": "新竹市→國道3號、1號→臺北市",
                    "en": "Hsinchu City→National Freeway No. 3 and No.1→Taipei City"
                }
            }
        ],
        "departure": {
            "zh": "仁愛敦化路口(圓環)",
            "en": "Renai &amp; Dunhua Intersection (Circle)"
        },
        "destination": {
            "zh": "新竹轉運站",
            "en": "Hsinchu bus station"
        }
    },
    {
        "code": 1,
        "routeID": "THB2011",
        "routeName": {
            "zh": "2011",
            "en": "2011"
        },
        "subroute": [
            {
                "subrouteID": "THB20110",
                "subrouteName": {
                    "zh": "2011",
                    "en": "2011"
                },
                "headsign": {
                    "zh": "臺北市－新竹轉運站",
                    "en": "Taipei City→Hsinchu bus station"
                }
            },
            {
                "subrouteID": "THB20110",
                "subrouteName": {
                    "zh": "2011",
                    "en": "2011"
                },
                "headsign": {
                    "zh": "新竹轉運站－臺北市",
                    "en": "Hsinchu bus station→Taipei City"
                }
            },
            {
                "subrouteID": "THB2011B",
                "subrouteName": {
                    "zh": "2011B",
                    "en": "2011B"
                },
                "headsign": {
                    "zh": "新竹香山牧場－臺北市[經茄苳交流道]",
                    "en": "Hsinchu Xiangshan ranch→Taipei City(Via Jiadong Interchange)"
                }
            },
            {
                "subrouteID": "THB2011C",
                "subrouteName": {
                    "zh": "2011C",
                    "en": "2011C"
                },
                "headsign": {
                    "zh": "臺北市－新竹香山牧場[經茄苳交流道]",
                    "en": "Taipei City→Hsinchu Xiangshan ranch(Via Jiadong Interchange)"
                }
            },
            {
                "subrouteID": "THB2011C",
                "subrouteName": {
                    "zh": "2011C",
                    "en": "2011C"
                },
                "headsign": {
                    "zh": "新竹香山牧場－臺北市[經茄苳交流道]",
                    "en": "Hsinchu Xiangshan ranch→Taipei City(Via Jiadong Interchange)"
                }
            }
        ],
        "departure": {
            "zh": "臺北轉運站",
            "en": "Taipei Bus Station"
        },
        "destination": {
            "zh": "新竹轉運站",
            "en": "Hsinchu bus station"
        }
    },
    {
        "code": 1,
        "routeID": "THB1804",
        "routeName": {
            "zh": "1804",
            "en": "1804"
        },
        "subroute": [
            {
                "subrouteID": "THB18040",
                "subrouteName": {
                    "zh": "1804",
                    "en": "1804"
                },
                "headsign": {
                    "zh": "基隆→新竹",
                    "en": "Keelung→Hsinchu"
                }
            },
            {
                "subrouteID": "THB18040",
                "subrouteName": {
                    "zh": "1804",
                    "en": "1804"
                },
                "headsign": {
                    "zh": "新竹→基隆",
                    "en": "Hsinchu→Keelung"
                }
            },
            {
                "subrouteID": "THB1804A",
                "subrouteName": {
                    "zh": "1804A",
                    "en": "1804A"
                },
                "headsign": {
                    "zh": "基隆→新竹[不經林口站]",
                    "en": "Keelung→Hsinchu(not via Linkou Station)"
                }
            },
            {
                "subrouteID": "THB1804A",
                "subrouteName": {
                    "zh": "1804A",
                    "en": "1804A"
                },
                "headsign": {
                    "zh": "新竹→基隆[不經林口站]",
                    "en": "Hsinchu→Keelung(Not Via Linkou Station)"
                }
            }
        ],
        "departure": {
            "zh": "基隆站(國光)",
            "en": "Keelung Station(KUO-KUANG)"
        },
        "destination": {
            "zh": "新竹轉運站",
            "en": "Hsinchu Bus Station"
        }
    },
    {
        "code": 1,
        "routeID": "THB1822",
        "routeName": {
            "zh": "1822",
            "en": "1822"
        },
        "subroute": [
            {
                "subrouteID": "THB18220",
                "subrouteName": {
                    "zh": "1822",
                    "en": "1822"
                },
                "headsign": {
                    "zh": "臺北→新竹",
                    "en": "Taipei→Hsinchu"
                }
            },
            {
                "subrouteID": "THB18220",
                "subrouteName": {
                    "zh": "1822",
                    "en": "1822"
                },
                "headsign": {
                    "zh": "新竹→臺北",
                    "en": "Hsinchu→Taipei"
                }
            },
            {
                "subrouteID": "THB1822A",
                "subrouteName": {
                    "zh": "1822A",
                    "en": "1822A"
                },
                "headsign": {
                    "zh": "臺北→新竹[經中華大學]",
                    "en": "Taipei→Hsinchu(Via Chung Hua University)"
                }
            },
            {
                "subrouteID": "THB1822A",
                "subrouteName": {
                    "zh": "1822A",
                    "en": "1822A"
                },
                "headsign": {
                    "zh": "新竹→臺北[經中華大學]",
                    "en": "Hsinchu→Taipei(Via Chung Hua University)"
                }
            }
        ],
        "departure": {
            "zh": "臺北轉運站",
            "en": "Taipei Bus Station"
        },
        "destination": {
            "zh": "新竹轉運站",
            "en": "Hsinchu Bus Station"
        }
    },
    {
        "code": 1,
        "routeID": "THB1865",
        "routeName": {
            "zh": "1865",
            "en": "1865"
        },
        "subroute": [
            {
                "subrouteID": "THB18650",
                "subrouteName": {
                    "zh": "1865",
                    "en": "1865"
                },
                "headsign": {
                    "zh": "新竹→林口",
                    "en": "Hsinchu→Linkou"
                }
            },
            {
                "subrouteID": "THB18650",
                "subrouteName": {
                    "zh": "1865",
                    "en": "1865"
                },
                "headsign": {
                    "zh": "林口→新竹",
                    "en": "Linkou→Hsinchu"
                }
            }
        ],
        "departure": {
            "zh": "新竹轉運站",
            "en": "Hsinchu bus station"
        },
        "destination": {
            "zh": "桃園長庚轉運站",
            "en": "Taoyuan Changgung Bus Station"
        }
    },
    {
        "code": 1,
        "routeID": "THB1866",
        "routeName": {
            "zh": "1866",
            "en": "1866"
        },
        "subroute": [
            {
                "subrouteID": "THB18660",
                "subrouteName": {
                    "zh": "1866",
                    "en": "1866"
                },
                "headsign": {
                    "zh": "新竹→臺中",
                    "en": "Hsinchu→Taichung"
                }
            },
            {
                "subrouteID": "THB18660",
                "subrouteName": {
                    "zh": "1866",
                    "en": "1866"
                },
                "headsign": {
                    "zh": "臺中→新竹",
                    "en": "Taichung→Hsinchu"
                }
            },
            {
                "subrouteID": "THB1866A",
                "subrouteName": {
                    "zh": "1866A",
                    "en": "1866A"
                },
                "headsign": {
                    "zh": "新竹→臺中[經元培大學]",
                    "en": "Hsinchu→Taichung(Via Yuanpei University)"
                }
            },
            {
                "subrouteID": "THB1866A",
                "subrouteName": {
                    "zh": "1866A",
                    "en": "1866A"
                },
                "headsign": {
                    "zh": "臺中→新竹[經元培大學]",
                    "en": "Taichung→Hsinchu(Via Yuanpei University)"
                }
            },
            {
                "subrouteID": "THB1866B",
                "subrouteName": {
                    "zh": "1866B",
                    "en": "1866B"
                },
                "headsign": {
                    "zh": "新竹→臺中(不經科技生活館站)",
                    "en": "Hsinchu→Taichung(not via Science Park Life Hub)"
                }
            },
            {
                "subrouteID": "THB1866B",
                "subrouteName": {
                    "zh": "1866B",
                    "en": "1866B"
                },
                "headsign": {
                    "zh": "臺中→新竹(不經科技生活館站)",
                    "en": "Taichung→Hsinchu(not via Science Park Life Hub)"
                }
            }
        ],
        "departure": {
            "zh": "新竹轉運站",
            "en": "Hsinchu bus station"
        },
        "destination": {
            "zh": "國光客運臺中車站",
            "en": "Taichung Bus Terminal (KUO-KUANG)"
        }
    },
    {
        "code": 1,
        "routeID": "THB9003",
        "routeName": {
            "zh": "9003",
            "en": "9003"
        },
        "subroute": [
            {
                "subrouteID": "THB90030",
                "subrouteName": {
                    "zh": "9003",
                    "en": "9003"
                },
                "headsign": {
                    "zh": "臺北市→國道1號高速公路→新竹市",
                    "en": "Taipei City→National Freeway No.1→Hsinchu City"
                }
            },
            {
                "subrouteID": "THB90030",
                "subrouteName": {
                    "zh": "9003",
                    "en": "9003"
                },
                "headsign": {
                    "zh": "新竹市→國道1號高速公路→臺北市",
                    "en": "Hsinchu City→National Freeway No.1→Taipei City"
                }
            }
        ],
        "departure": {
            "zh": "臺北轉運站",
            "en": "Taipei Bus Station"
        },
        "destination": {
            "zh": "新竹轉運站",
            "en": "Hsinchu bus station"
        }
    },
    {
        "code": 1,
        "routeID": "THB9010",
        "routeName": {
            "zh": "9010",
            "en": "9010"
        },
        "subroute": [
            {
                "subrouteID": "THB90100",
                "subrouteName": {
                    "zh": "9010",
                    "en": "9010"
                },
                "headsign": {
                    "zh": "臺中市→國道１號→新竹市",
                    "en": "Taichung City→National Freeway No. 1→Hsinchu City"
                }
            },
            {
                "subrouteID": "THB90100",
                "subrouteName": {
                    "zh": "9010",
                    "en": "9010"
                },
                "headsign": {
                    "zh": "新竹市→國道１號→臺中市",
                    "en": "Hsinchu City→National Freeway No. 1→Taichung City"
                }
            },
            {
                "subrouteID": "THB9010A",
                "subrouteName": {
                    "zh": "9010A",
                    "en": "9010A"
                },
                "headsign": {
                    "zh": "臺中市→國道１號→新竹市[經大雅交流道]",
                    "en": "Taichung City→National Freeway No. 1→Hsinchu City[Via Daya Interchange]"
                }
            },
            {
                "subrouteID": "THB9010A",
                "subrouteName": {
                    "zh": "9010A",
                    "en": "9010A"
                },
                "headsign": {
                    "zh": "新竹市→國道１號→臺中市[經大雅交流道]",
                    "en": "Hsinchu City→National Freeway No. 1→Taichung City[Via Daya Interchange]"
                }
            }
        ],
        "departure": {
            "zh": "臺中車站(大智北路)",
            "en": "Taichung Station(Dazhi North Road)"
        },
        "destination": {
            "zh": "新竹轉運站",
            "en": "Hsinchu bus station"
        }
    }
]
